dfit_toolkit-1.0.0.dist-info/licenses/LICENSE
src/__init__.py
src/cli/__init__.py
src/cli/completion.py
src/cli/main.py
src/cli/utils.py
src/core/__init__.py
src/core/file_utils.py
src/core/gps_utilities.py
src/core/metadata_analyzer.py
src/core/steganography_detector.py
src/core/tampering_detector.py
dfit_toolkit-1.0.0.dist-info/METADATA
dfit_toolkit-1.0.0.dist-info/WHEEL
dfit_toolkit-1.0.0.dist-info/entry_points.txt
dfit_toolkit-1.0.0.dist-info/top_level.txt
dfit_toolkit-1.0.0.dist-info/RECORD
