Metadata-Version: 2.4
Name: dfit-toolkit
Version: 1.0.0
Summary: A comprehensive command-line forensics toolkit for digital image analysis
Home-page: https://github.com/C0d3-cr4f73r/DFIT
Author: C0d3-cr4f73r
Author-email: 
License: MIT
Project-URL: Homepage, https://github.com/C0d3-cr4f73r/DFIT
Project-URL: Documentation, https://github.com/C0d3-cr4f73r/DFIT#readme
Project-URL: Repository, https://github.com/C0d3-cr4f73r/DFIT
Project-URL: Bug Tracker, https://github.com/C0d3-cr4f73r/DFIT/issues
Keywords: forensics,image-analysis,steganography,tampering-detection,metadata,EXIF,digital-forensics,security,CLI
Classifier: Development Status :: 4 - Beta
Classifier: Intended Audience :: Developers
Classifier: Intended Audience :: Science/Research
Classifier: Intended Audience :: Legal Industry
Classifier: Topic :: Security
Classifier: Topic :: Scientific/Engineering :: Image Recognition
Classifier: License :: OSI Approved :: MIT License
Classifier: Programming Language :: Python :: 3
Classifier: Programming Language :: Python :: 3.8
Classifier: Programming Language :: Python :: 3.9
Classifier: Programming Language :: Python :: 3.10
Classifier: Programming Language :: Python :: 3.11
Classifier: Programming Language :: Python :: 3.12
Classifier: Operating System :: OS Independent
Classifier: Environment :: Console
Requires-Python: >=3.8
License-File: LICENSE
Requires-Dist: pillow==10.3.0
Requires-Dist: exifread==3.0.0
Requires-Dist: click==8.1.7
Requires-Dist: numpy==1.26.4
Requires-Dist: opencv-python-headless==4.10.0.84
Dynamic: home-page
Dynamic: license-file
Dynamic: requires-python
